<?xml version="1.0" encoding="utf-8"?>
<conversions>
  <codeFramework>
    <conversion methodName="AddPrereqComponent" xmlName="prerequisite">
      <attribute name="name"/>
      <attribute name="access"/>
      <attribute name="export" transcode="export"/>
      <attribute name="expose"/>
    </conversion>
    <conversion methodName="AddPrereqAuthorization" xmlName="authorize">
      <attribute name="name"/>
      <attribute name="access"/>
    </conversion>
    <conversion methodName="AttachComponent" xmlName="attached">
      <attribute name="name"/>
    </conversion>
    <conversion methodName="SetNotBuilt" xmlName="built">
      <attribute name="value" default="false"/>
    </conversion>
    <conversion methodName="SetNotTransitiveBuilt" xmlName="transitive">
      <attribute name="value" default="false"/>
    </conversion>
    <conversion methodName="SetDescription" xmlName="description">
      <value/>
    </conversion>
    <conversion methodName="SetCopyright" xmlName="copyright">
      <attribute name="value"/>
    </conversion>
    <conversion methodName="SetSubOSBuildtime" xmlName="subOsBuildtime">
      <attribute name="value"/>
    </conversion>
    <conversion methodName="SetLicense" xmlName="licence">
      <attribute name="value"/>
    </conversion>
    <conversion methodName="SetBrand" xmlName="brand" groupName="brands">
      <attribute name="name"/>
    </conversion>
    <conversion methodName="NoCheckOnPrereq" xmlName="checkOnPrereq">
      <attribute name="value" default="false"/>
    </conversion>
  </codeFramework>
  <testFramework>
    <conversion methodName="AddPrereqComponent" xmlName="prerequisite">
      <attribute name="name"/>
      <attribute name="access"/>
      <attribute name="export" transcode="export"/>
      <attribute name="expose"/>
    </conversion>
    <conversion methodName="AddPrereqAuthorization" xmlName="authorize">
      <attribute name="name"/>
      <attribute name="access"/>
    </conversion>
    <conversion methodName="AttachComponent" xmlName="attached">
      <attribute name="name"/>
    </conversion>
    <conversion methodName="SetNotBuilt" xmlName="built">
      <attribute name="value" default="false"/>
    </conversion>
    <conversion methodName="SetNotTransitiveBuilt" xmlName="transitive">
      <attribute name="value" default="false"/>
    </conversion>
    <conversion methodName="SetDescription" xmlName="description">
      <value/>
    </conversion>
    <conversion methodName="SetCopyright" xmlName="copyright">
      <attribute name="value"/>
    </conversion>
    <conversion methodName="SetSubOSBuildtime" xmlName="subOsBuildtime">
      <attribute name="value"/>
    </conversion>
    <conversion methodName="SetLicense" xmlName="licence">
      <attribute name="value"/>
    </conversion>
    <conversion methodName="SetBrand" xmlName="brand" groupName="brands">
      <attribute name="name"/>
    </conversion>
  </testFramework>
  <eduFramework>
    <conversion methodName="AddPrereqComponent" xmlName="prerequisite">
      <attribute name="name"/>
      <attribute name="access"/>
      <attribute name="export" transcode="export"/>
      <attribute name="expose"/>
    </conversion>
    <conversion methodName="AddPrereqAuthorization" xmlName="authorize">
      <attribute name="name"/>
      <attribute name="access"/>
    </conversion>
    <conversion methodName="AttachComponent" xmlName="attached">
      <attribute name="name"/>
    </conversion>
    <conversion methodName="SetNotBuilt" xmlName="built">
      <attribute name="value" default="false"/>
    </conversion>
    <conversion methodName="SetNotTransitiveBuilt" xmlName="transitive">
      <attribute name="value" default="false"/>
    </conversion>
    <conversion methodName="SetDescription" xmlName="description">
      <value/>
    </conversion>
    <conversion methodName="SetCopyright" xmlName="copyright">
      <attribute name="value"/>
    </conversion>
    <conversion methodName="SetSubOSBuildtime" xmlName="subOsBuildtime">
      <attribute name="value"/>
    </conversion>
    <conversion methodName="SetLicense" xmlName="licence">
      <attribute name="value"/>
    </conversion>
    <conversion methodName="SetBrand" xmlName="brand" groupName="brands">
      <attribute name="name"/>
    </conversion>
  </eduFramework>
  <product>
    <conversion methodName="SetDescription" xmlName="description">
      <value/>
    </conversion>
    <conversion methodName="SetCopyright" xmlName="copyright">
      <attribute name="value"/>
    </conversion>
    <conversion methodName="SetLicense" xmlName="license">
      <attribute name="value"/>
    </conversion>
    <conversion methodName="SetBrand" xmlName="brand" groupName="brands">
      <attribute name="name"/>
    </conversion>
    <conversion methodName="AuthorizeComponent" xmlName="authorizedComponent">
      <attribute name="name"/>
      <attribute name="scale" transcode="scale"/>
    </conversion>
    <conversion methodName="SetMarketingType" xmlName="marketingType">
      <attribute name="name"/>
    </conversion>
    <conversion methodName="SetLicenseType" xmlName="licenseType">
      <attribute name="name"/>
    </conversion>
    <conversion methodName="IncludeProgDoc" xmlName="includedProgDoc">
      <attribute name="name"/>
    </conversion>
    <conversion methodName="IncludeDoc" xmlName="includedDoc">
      <attribute name="name"/>
    </conversion>
    <conversion methodName="IncludeRefDoc" xmlName="includedRefDoc">
      <attribute name="name"/>
    </conversion>
    <conversion methodName="AllowedWorkbench" xmlName="allowedWorkbench">
      <attribute name="name"/>
    </conversion>
    <conversion methodName="IncludeUseCaseCode" xmlName="includedUseCaseCode">
      <attribute name="name"/>
    </conversion>
    <conversion methodName="AllowExtra" xmlName="allowExtra">
      <attribute name="value" default="true"/>
    </conversion>
    <conversion methodName="SetPartner" xmlName="partner">
      <attribute name="name"/>
    </conversion>
    <conversion methodName="AddPrereqComponent" xmlName="prerequisiteComponent">
      <attribute name="name"/>
    </conversion>
    <conversion methodName="IncludeHeaders" xmlName="includedHeader">
      <attribute name="name"/>
    </conversion>
    <conversion methodName="SetScale" xmlName="scale">
      <attribute name="value"/>
    </conversion>
    <conversion methodName="AuthorizeOption" xmlName="authorizedOption">
      <attribute name="name"/>
      <attribute name="scale" transcode="scale"/>
    </conversion>
    <conversion methodName="IncludeComponent" xmlName="includedComponent">
      <attribute name="name"/>
     </conversion>
    <conversion methodName="IncludeExtraComponent" xmlName="includedExtraComponent">
      <attribute name="name"/>
    </conversion>
  </product>
  <component>
    <conversion methodName="IncludeComponent" xmlName="includedComponent">
      <attribute name="name"/>
    </conversion>
    <conversion methodName="IncludeExtraComponent" xmlName="includedExtraComponent">
      <attribute name="name"/>
    </conversion>
    <conversion methodName="IncludeProgDoc" xmlName="includedProgDoc">
      <attribute name="name"/>
    </conversion>
    <conversion methodName="IncludeDoc" xmlName="includedDoc">
      <attribute name="name"/>
    </conversion>
    <conversion methodName="IncludeRefDoc" xmlName="includedRefDoc">
      <attribute name="name"/>
    </conversion>
    <conversion methodName="IncludeUseCaseCode" xmlName="includedUseCaseCode">
      <attribute name="name"/>
    </conversion>
    <conversion methodName="AuthorizeComponent" xmlName="authorizedComponent">
      <attribute name="name"/>
      <attribute name="scale" transcode="scale"/>
    </conversion>
    <conversion methodName="IncludeHeaders" xmlName="includedHeader">
      <attribute name="name"/>
    </conversion>
    <conversion methodName="AuthorizeOption" xmlName="authorizedOption">
      <attribute name="name"/>
      <attribute name="scale" transcode="scale"/>
    </conversion>
    <conversion methodName="AllowedWorkbench" xmlName="allowedWorkbench">
      <attribute name="name"/>
    </conversion>
  </component>
  <configuration>
    <conversion methodName="SetDescription" xmlName="description">
      <value/>
    </conversion>
    <conversion methodName="SetCopyright" xmlName="copyright">
      <attribute name="value"/>
    </conversion>
    <conversion methodName="SetLicense" xmlName="license">
      <attribute name="value"/>
    </conversion>
    <conversion methodName="AuthorizeComponent" xmlName="authorizedComponent">
      <attribute name="name"/>
      <attribute name="scale" transcode ="scale"/>
    </conversion>
    <conversion methodName="SetMarketingType" xmlName="marketingType">
      <attribute name="name"/>
    </conversion>
    <conversion methodName="SetLicenseType" xmlName="licenseType">
      <attribute name="name"/>
    </conversion>
    <conversion methodName="SetScale" xmlName="scale">
      <attribute name="value"/>
    </conversion>
    <conversion methodName="IncludeComponent" xmlName="includedComponent">
      <attribute name="name"/>
    </conversion>
    <conversion methodName="AddPrereqComponent" xmlName="prerequisiteComponent">
      <attribute name="name"/>
    </conversion>
    <conversion methodName="IncludeExtraComponent" xmlName="includedExtraComponent">
      <attribute name="name"/>
    </conversion>
    <conversion methodName="SetPartner" xmlName="partner">
      <attribute name="name"/>
    </conversion>
    <conversion methodName="AuthorizeOption" xmlName="authorizedOption">
      <attribute name="name"/>
      <attribute name="scale" transcode="scale"/>
    </conversion>
  </configuration>
  <media>
    <conversion methodName="SetDescription" xmlName="description">
      <value/>
    </conversion>
    <conversion methodName="SetCopyright" xmlName="copyright">
      <attribute name="value"/>
    </conversion>
    <conversion methodName="SetLicense" xmlName="licence">
      <attribute name="value"/>
    </conversion>
    <conversion methodName="IncludeComponent" xmlName="includedComponent">
      <attribute name="name"/>
      <attribute name="os"/>
    </conversion>
    <conversion methodName="SetMarketingVersion" xmlName="marketingVersion">
      <attribute name="value"/>
    </conversion>
    <conversion methodName="SetProductItem" xmlName="productItem">
      <attribute name="value"/>
    </conversion>
    <conversion methodName="SetProductLine" xmlName="productLine">
      <attribute name="value"/>
    </conversion>
  </media>
  <transcodes>
    <transcode name="scale">
      <param from="1" to ="P1"/>
      <param from="2" to ="P2"/>
      <param from="3" to ="P3"/>
    </transcode>
    <transcode name="export">
      <param from="AddToClientPrereqs" to ="AddToClientPrereqs"/>
      <param from="DoNotAddToClientPrereqs" to ="DoNotAddToClientPrereqs"/>
      <param from="AddToClientNotSpecified" to ="AddToClientNotSpecified"/>
      <param from="NotExported" to =""/>
      <param from="Exported" to =""/>
    </transcode>
  </transcodes>
</conversions>
