<?xml version="1.0" encoding="UTF-8" ?>
<!--XML file for setting used by ELB application 2010 -->
<st:repository xsi:schemaLocation="urn:com:dassault_systemes:settings settings.xsd" xmlns:st="urn:com:dassault_systemes:settings" xmlns="urn:com:dassault_systemes:settings" xmlns:xsi="http://www.w3.org/2001/XMLSchema-instance">
	<st:Description name="E3DMigrationOptions" PrimaryTabpage="/General/Compatibility/Electrical" >
		<st:role>Options to set while migrating data from V4 to V5</st:role>
		<st:detailedRole>Options to set while migrating data from V4 to V5</st:detailedRole>
		<st:RepositoryFile>E3DMigrationOptions</st:RepositoryFile>
		<st:version>1</st:version>
		<st:compatibility>
			<st:FullCompatibilityfromLevel>1</st:FullCompatibilityfromLevel>
			<st:UpwardCompatibilityfromLevel>1</st:UpwardCompatibilityfromLevel>
		</st:compatibility>
	</st:Description>
	<st:attributes>
		<st:attribute Name="Option">
			<st:role>Bundle segment migration mode</st:role>
			<st:detailedRole>Bundle segment can be migrated as a bundle segment OR multi-branchable document</st:detailedRole>
			<st:string Unicode="false">
				<st:enum>
					<st:role>Migrate V4 BNSs to a V5 multi-branchable document. All the V4 BNSs of a given V4 GBN will result in a multi-branchable document: a single CATPart.</st:role>
					<st:value>"IdBranchable"</st:value>
					<st:role>Migrate V4 BNSs to V5 bundle segments. Each V5 bundle segment will have its own CATPart document.</st:role>
					<st:value>"IdBNS"</st:value>
				</st:enum>
				<st:default>
					<st:value>IdBranchable</st:value>
				</st:default>
			</st:string>
		</st:attribute>
		<st:attribute Name="GBNOptions">
			<st:role>Geometrical bundle migration mode</st:role>
			<st:detailedRole>Geometrical bundle can be migrated as a component OR product document </st:detailedRole>
			<st:string Unicode="false">
				<st:enum>
					<st:role>Migrate Geometrical bundle as a CATProduct.</st:role>
					<st:value>"IdProduct"</st:value>
					<st:role>Migrate Geometrical bundle as a component.</st:role>
					<st:value>"IdComponent"</st:value>
				</st:enum>
				<st:default>
					<st:value>IdProduct</st:value>
				</st:default>
			</st:string>
		</st:attribute>
		<st:attribute Name="ShellOptions">
			<st:role>Shell migration mode</st:role>
			<st:detailedRole></st:detailedRole>
			<st:string Unicode="false">
				<st:enum>
					<st:role>Migrate the Shells With Electrical Behavior.</st:role>
					<st:value>"IdMigration"</st:value>
					<st:role>Migrate Shells Without Electrical Behavior.</st:role>
					<st:value>"IdGeomRep"</st:value>
				</st:enum>
				<st:default>
					<st:value>IdMigration</st:value>
				</st:default>
			</st:string>
		</st:attribute>
	</st:attributes>
</st:repository>
